orca_driver_interface/__init__.py
orca_driver_interface/driver_interfaces.py
orca_driver_interface/py.typed
orca_driver_interface/transporter_interfaces.py
orca_interfaces-0.1.0.dist-info/METADATA
orca_interfaces-0.1.0.dist-info/WHEEL
orca_interfaces-0.1.0.dist-info/top_level.txt
orca_interfaces-0.1.0.dist-info/RECORD
